{
  "generatedAt": "2026-07-20T22:35:38.379372+00:00",
  "source": "https://dashboard.dpo.cz/api/server",
  "count": 14,
  "typeCounts": {
    "tram": 5,
    "bus": 9
  },
  "vehicles": [
    {
      "id": "DPO.VEH.00998",
      "vehicleNumber": 998,
      "route": "18",
      "type": "tram",
      "agencyName": "DPO a.s.",
      "headSign": "Hlavní nádraží",
      "tripFrom": null,
      "tripTo": null,
      "finalStopName": "Hlavní nádraží",
      "lastStopName": "Ferona",
      "state": "ride",
      "delaySeconds": -1,
      "delayLabel": "On time",
      "delayState": "nodelay",
      "engineType": null,
      "isBarrierLess": false,
      "airCondition": false,
      "securityCamera": true,
      "apc": false,
      "lat": 49.814518,
      "lng": 18.2392178,
      "modelName": "Tatra T3R.P",
      "image": "https://scc.dpo.cz/Content/Files/a66d57ed-dbde-45ae-8b57-965ef1b7ce77.jpg",
      "licensePlate": "",
      "commissioning": "1988-01-01 00:00:00",
      "seating": 30,
      "standing": 70,
      "jointCount": 0,
      "carriage": 1,
      "totalKm": 2007789.55
    },
    {
      "id": "DPO.VEH.01002",
      "vehicleNumber": 1002,
      "route": "18",
      "type": "tram",
      "agencyName": "DPO a.s.",
      "headSign": "Dubina",
      "tripFrom": "Dubina",
      "tripTo": "Hlavní nádraží",
      "finalStopName": "Dubina",
      "lastStopName": "Prostorná",
      "state": "ride",
      "delaySeconds": 0,
      "delayLabel": "On time",
      "delayState": "nodelay",
      "engineType": "electric",
      "isBarrierLess": false,
      "airCondition": false,
      "securityCamera": false,
      "apc": false,
      "lat": 49.82686,
      "lng": 18.2499352,
      "modelName": "Tatra T3R.P",
      "image": "https://scc.dpo.cz/Content/Files/a66d57ed-dbde-45ae-8b57-965ef1b7ce77.jpg",
      "licensePlate": "",
      "commissioning": "1987-12-01 00:00:00",
      "seating": 30,
      "standing": 70,
      "jointCount": 0,
      "carriage": 1,
      "totalKm": 2043657.129
    },
    {
      "id": "DPO.VEH.01353",
      "vehicleNumber": 1353,
      "route": "4",
      "type": "tram",
      "agencyName": "DPO a.s.",
      "headSign": "Martinov",
      "tripFrom": null,
      "tripTo": null,
      "finalStopName": "Martinov",
      "lastStopName": "Mariánské náměstí",
      "state": "ride",
      "delaySeconds": 15,
      "delayLabel": "On time",
      "delayState": "nodelay",
      "engineType": "electric",
      "isBarrierLess": true,
      "airCondition": false,
      "securityCamera": true,
      "apc": true,
      "lat": 49.8271751,
      "lng": 18.2519531,
      "modelName": "Pragoimex VarioLFR.E",
      "image": "https://scc.dpo.cz/Content/Files/06a3dda1-7993-4a50-a5a5-96709b00c5fa.jpg",
      "licensePlate": "",
      "commissioning": "1984-01-01 00:00:00",
      "seating": 31,
      "standing": 77,
      "jointCount": 0,
      "carriage": 1,
      "totalKm": 912569.226
    },
    {
      "id": "DPO.VEH.01365",
      "vehicleNumber": 1365,
      "route": "7",
      "type": "tram",
      "agencyName": "DPO a.s.",
      "headSign": "Poruba,Vřesinská",
      "tripFrom": null,
      "tripTo": null,
      "finalStopName": "Poruba,Vřesinská",
      "lastStopName": "Ferona",
      "state": "ride",
      "delaySeconds": -2,
      "delayLabel": "On time",
      "delayState": "nodelay",
      "engineType": "electric",
      "isBarrierLess": true,
      "airCondition": false,
      "securityCamera": true,
      "apc": true,
      "lat": 49.8144073,
      "lng": 18.2393627,
      "modelName": "Pragoimex VarioLFR.S",
      "image": "https://scc.dpo.cz/Content/Files/2950fd75-ad06-40a1-a0c4-99b01b941014.jpg",
      "licensePlate": "",
      "commissioning": "1988-01-01 00:00:00",
      "seating": 31,
      "standing": 77,
      "jointCount": 0,
      "carriage": 1,
      "totalKm": 792704.537
    },
    {
      "id": "DPO.VEH.01367",
      "vehicleNumber": 1367,
      "route": "7",
      "type": "tram",
      "agencyName": "DPO a.s.",
      "headSign": "Výškovice",
      "tripFrom": null,
      "tripTo": null,
      "finalStopName": "Výškovice",
      "lastStopName": "Svinov,mosty",
      "state": "ride",
      "delaySeconds": -4,
      "delayLabel": "On time",
      "delayState": "nodelay",
      "engineType": "electric",
      "isBarrierLess": true,
      "airCondition": false,
      "securityCamera": true,
      "apc": true,
      "lat": 49.82409,
      "lng": 18.2114334,
      "modelName": "Pragoimex VarioLFR.S",
      "image": "https://scc.dpo.cz/Content/Files/2950fd75-ad06-40a1-a0c4-99b01b941014.jpg",
      "licensePlate": "",
      "commissioning": "1988-01-01 00:00:00",
      "seating": 31,
      "standing": 77,
      "jointCount": 0,
      "carriage": 1,
      "totalKm": 780165.39
    },
    {
      "id": "DPO.VEH.07141",
      "vehicleNumber": 7141,
      "route": "43",
      "type": "bus",
      "agencyName": "DPO a.s.",
      "headSign": "Poruba,Opavská",
      "tripFrom": null,
      "tripTo": null,
      "finalStopName": "Poruba,Opavská",
      "lastStopName": "Bedřicha Nikodema",
      "state": "ride",
      "delaySeconds": 92,
      "delayLabel": "2 min delay",
      "delayState": "delay",
      "engineType": "cng",
      "isBarrierLess": true,
      "airCondition": false,
      "securityCamera": true,
      "apc": true,
      "lat": 49.845005,
      "lng": 18.18239,
      "modelName": "Solaris Urbino 12 CNG",
      "image": "https://scc.dpo.cz/Content/Files/58e36959-6b2a-427f-b194-f74fc779da04.jpg",
      "licensePlate": "9T75766",
      "commissioning": "2015-10-21 00:00:00",
      "seating": 28,
      "standing": 58,
      "jointCount": 0,
      "carriage": 1,
      "totalKm": 824636.291
    },
    {
      "id": "DPO.VEH.07156",
      "vehicleNumber": 7156,
      "route": "76",
      "type": "bus",
      "agencyName": "DPO a.s.",
      "headSign": "Klimkovice,centrum",
      "tripFrom": null,
      "tripTo": null,
      "finalStopName": "Klimkovice,centrum",
      "lastStopName": "Horní Polanka",
      "state": "ride",
      "delaySeconds": 66,
      "delayLabel": "1 min delay",
      "delayState": "delay",
      "engineType": "cng",
      "isBarrierLess": true,
      "airCondition": false,
      "securityCamera": true,
      "apc": true,
      "lat": 49.78728,
      "lng": 18.1671543,
      "modelName": "Solaris Urbino 12 CNG",
      "image": "https://scc.dpo.cz/Content/Files/58e36959-6b2a-427f-b194-f74fc779da04.jpg",
      "licensePlate": "9T74950",
      "commissioning": "2015-10-16 00:00:00",
      "seating": 28,
      "standing": 58,
      "jointCount": 0,
      "carriage": 1,
      "totalKm": 581115.591
    },
    {
      "id": "DPO.VEH.07165",
      "vehicleNumber": 7165,
      "route": "43",
      "type": "bus",
      "agencyName": "DPO a.s.",
      "headSign": "Svinov,mosty",
      "tripFrom": null,
      "tripTo": null,
      "finalStopName": "Svinov,mosty",
      "lastStopName": "Řecká",
      "state": "ride",
      "delaySeconds": 56,
      "delayLabel": "1 min delay",
      "delayState": "nodelay",
      "engineType": "cng",
      "isBarrierLess": true,
      "airCondition": false,
      "securityCamera": true,
      "apc": true,
      "lat": 49.82569,
      "lng": 18.2024174,
      "modelName": "Solaris Urbino 12 CNG",
      "image": "https://scc.dpo.cz/Content/Files/58e36959-6b2a-427f-b194-f74fc779da04.jpg",
      "licensePlate": "9T75348",
      "commissioning": "2015-10-16 00:00:00",
      "seating": 28,
      "standing": 58,
      "jointCount": 0,
      "carriage": 1,
      "totalKm": 632024.938
    },
    {
      "id": "DPO.VEH.07184",
      "vehicleNumber": 7184,
      "route": "77",
      "type": "bus",
      "agencyName": "DPO a.s.",
      "headSign": "Hrabová,statek",
      "tripFrom": null,
      "tripTo": null,
      "finalStopName": "Hrabová,statek",
      "lastStopName": "Bělská",
      "state": "ride",
      "delaySeconds": 58,
      "delayLabel": "1 min delay",
      "delayState": "nodelay",
      "engineType": "cng",
      "isBarrierLess": true,
      "airCondition": false,
      "securityCamera": true,
      "apc": true,
      "lat": 49.76125,
      "lng": 18.2938156,
      "modelName": "Solaris Urbino 12 CNG",
      "image": "https://scc.dpo.cz/Content/Files/58e36959-6b2a-427f-b194-f74fc779da04.jpg",
      "licensePlate": "9T72574",
      "commissioning": "2015-10-21 00:00:00",
      "seating": 28,
      "standing": 58,
      "jointCount": 0,
      "carriage": 1,
      "totalKm": 765100.784
    },
    {
      "id": "DPO.VEH.07229",
      "vehicleNumber": 7229,
      "route": "27",
      "type": "bus",
      "agencyName": "DPO a.s.",
      "headSign": "Proskovice",
      "tripFrom": null,
      "tripTo": null,
      "finalStopName": "Proskovice",
      "lastStopName": "Stará Bělá,křiž.",
      "state": "ride",
      "delaySeconds": 21,
      "delayLabel": "On time",
      "delayState": "nodelay",
      "engineType": "cng",
      "isBarrierLess": true,
      "airCondition": true,
      "securityCamera": true,
      "apc": true,
      "lat": 49.7558136,
      "lng": 18.2005043,
      "modelName": "Solaris Urbino 12 CNG",
      "image": "https://scc.dpo.cz/Content/Files/58e36959-6b2a-427f-b194-f74fc779da04.jpg",
      "licensePlate": "1TN0325",
      "commissioning": "2018-12-20 14:15:44",
      "seating": 30,
      "standing": 59,
      "jointCount": 0,
      "carriage": 2,
      "totalKm": 517774.022
    },
    {
      "id": "DPO.VEH.07764",
      "vehicleNumber": 7764,
      "route": "34",
      "type": "bus",
      "agencyName": "DPO a.s.",
      "headSign": "Křižíkova",
      "tripFrom": null,
      "tripTo": null,
      "finalStopName": "Křižíkova",
      "lastStopName": "Hošťálkovice,vysílač",
      "state": "ride",
      "delaySeconds": 71,
      "delayLabel": "1 min delay",
      "delayState": "delay",
      "engineType": "diesel",
      "isBarrierLess": true,
      "airCondition": false,
      "securityCamera": false,
      "apc": false,
      "lat": 49.85681,
      "lng": 18.2143383,
      "modelName": "Solaris Urbino 12",
      "image": "https://scc.dpo.cz/Content/Files/d511bb94-5bb7-48a8-b89f-aa91d91717dc.jpg",
      "licensePlate": "8T04992",
      "commissioning": "2012-07-17 00:00:00",
      "seating": 34,
      "standing": 62,
      "jointCount": 0,
      "carriage": 1,
      "totalKm": 1012741.291
    },
    {
      "id": "DPO.VEH.07774",
      "vehicleNumber": 7774,
      "route": "25",
      "type": "bus",
      "agencyName": "DPO a.s.",
      "headSign": "Vratimov,Horní Datyně",
      "tripFrom": null,
      "tripTo": null,
      "finalStopName": "Vratimov,Horní Datyně",
      "lastStopName": "Frýdecká",
      "state": "ride",
      "delaySeconds": 79,
      "delayLabel": "1 min delay",
      "delayState": "delay",
      "engineType": "diesel",
      "isBarrierLess": true,
      "airCondition": false,
      "securityCamera": true,
      "apc": false,
      "lat": 49.8005943,
      "lng": 18.2901936,
      "modelName": "Solaris Urbino 12",
      "image": "https://scc.dpo.cz/Content/Files/d511bb94-5bb7-48a8-b89f-aa91d91717dc.jpg",
      "licensePlate": "8T34677",
      "commissioning": "2012-09-27 00:00:00",
      "seating": 34,
      "standing": 62,
      "jointCount": 0,
      "carriage": 1,
      "totalKm": 862427.188
    },
    {
      "id": "DPO.VEH.07775",
      "vehicleNumber": 7775,
      "route": "71",
      "type": "bus",
      "agencyName": "DPO a.s.",
      "headSign": "Šenov,Volenství",
      "tripFrom": null,
      "tripTo": null,
      "finalStopName": "Šenov,Volenství",
      "lastStopName": "LDN",
      "state": "ride",
      "delaySeconds": 105,
      "delayLabel": "2 min delay",
      "delayState": "delay",
      "engineType": "diesel",
      "isBarrierLess": true,
      "airCondition": false,
      "securityCamera": true,
      "apc": false,
      "lat": 49.8174744,
      "lng": 18.3512783,
      "modelName": "Solaris Urbino 12",
      "image": "https://scc.dpo.cz/Content/Files/d511bb94-5bb7-48a8-b89f-aa91d91717dc.jpg",
      "licensePlate": "8T34678",
      "commissioning": "2012-09-27 00:00:00",
      "seating": 34,
      "standing": 62,
      "jointCount": 0,
      "carriage": 1,
      "totalKm": 948792.929
    },
    {
      "id": "DPO.VEH.07778",
      "vehicleNumber": 7778,
      "route": "71",
      "type": "bus",
      "agencyName": "DPO a.s.",
      "headSign": "Náměstí Republiky",
      "tripFrom": null,
      "tripTo": null,
      "finalStopName": "",
      "lastStopName": "U Samoobsluhy",
      "state": "ride",
      "delaySeconds": 61,
      "delayLabel": "1 min delay",
      "delayState": "delay",
      "engineType": "diesel",
      "isBarrierLess": true,
      "airCondition": false,
      "securityCamera": true,
      "apc": true,
      "lat": 49.80355,
      "lng": 18.356348,
      "modelName": "Solaris Urbino 12",
      "image": "https://scc.dpo.cz/Content/Files/d511bb94-5bb7-48a8-b89f-aa91d91717dc.jpg",
      "licensePlate": "8T57894",
      "commissioning": "2013-02-11 00:00:00",
      "seating": 34,
      "standing": 62,
      "jointCount": 0,
      "carriage": 1,
      "totalKm": 1040324.631
    }
  ]
}
